setup.py
pfind/__init__.py
pfind.egg-info/PKG-INFO
pfind.egg-info/SOURCES.txt
pfind.egg-info/dependency_links.txt
pfind.egg-info/top_level.txt