Metadata-Version: 1.0
Name: pfind
Version: 0
Summary: pFind Team
Home-page: http://pfind.org
Author: pFind Team
Author-email: pfind@ict.ac.cn
License: UNKNOWN
Platform: UNKNOWN
